autoscrap/__init__.py
autoscrap/cli.py
autoscrap/core.py
autoscrap-0.1.0.dist-info/METADATA
autoscrap-0.1.0.dist-info/WHEEL
autoscrap-0.1.0.dist-info/top_level.txt
autoscrap-0.1.0.dist-info/RECORD
