Metadata-Version: 2.4
Name: autoscrap
Version: 0.1.0
Summary: Lightweight Web Scraping Automation for Everyone
Home-page: https://pypi.org/project/autoscrap/
Author: Your Name
Author-email: your.email@example.com
License: MIT
Classifier: Programming Language :: Python :: 3
Classifier: License :: OSI Approved :: MIT License
Classifier: Operating System :: OS Independent
Classifier: Intended Audience :: End Users/Desktop
Classifier: Topic :: Software Development :: Libraries :: Python Modules
Classifier: Topic :: Utilities
Requires-Python: >=3.7
Requires-Dist: requests
Requires-Dist: beautifulsoup4
